Metadata-Version: 1.0
Name: dgds-distributions
Version: 0.1
Summary: Gaussian and Binomial distributions
Home-page: UNKNOWN
Author: Daniel Grewal
Author-email: daniel.grewal1503@icloud.com
License: UNKNOWN
Platform: UNKNOWN
